oda/__init__.py
oda/cache.py
oda/cli.py
oda/evaluator.py
oda/exceptions.py
oda/graph.py
oda/logs.py
oda/logstash.py
oda/sentry.py
oda/service_exception.py
oda/todestrieb.py
oda_client-1.3.40.dist-info/COPYING
oda_client-1.3.40.dist-info/METADATA
oda_client-1.3.40.dist-info/WHEEL
oda_client-1.3.40.dist-info/entry_points.txt
oda_client-1.3.40.dist-info/top_level.txt
oda_client-1.3.40.dist-info/RECORD
